CHANGELOG.md
shinyutils/__init__.py
shinyutils/_version.py
shinyutils/logng.py
shinyutils/matwrap.py
shinyutils/pt.py
shinyutils/py.typed
shinyutils/sh.py
shinyutils-12.4.0.dist-info/LICENSE
shinyutils-12.4.0.dist-info/WHEEL
shinyutils-12.4.0.dist-info/METADATA
shinyutils-12.4.0.dist-info/RECORD
